pyrandcracker/__init__.py
pyrandcracker/matrix_utils.py
pyrandcracker/randcracker.py
pyrandcracker/sagemath_support.py
pyrandcracker-0.3.6.dist-info/LICENSE
pyrandcracker-0.3.6.dist-info/METADATA
pyrandcracker-0.3.6.dist-info/WHEEL
pyrandcracker-0.3.6.dist-info/top_level.txt
pyrandcracker-0.3.6.dist-info/RECORD
