Metadata-Version: 2.1
Name: pyrandcracker
Version: 0.3.6
Summary: a better random cracker can predict python random lib number
Project-URL: Homepage, https://github.com/guoql666
Project-URL: Bug Tracker, https://github.com/guoql666/pyrandcracker/issues
Classifier: Development Status :: 3 - Alpha
Classifier: Programming Language :: Python :: 3
Classifier: License :: OSI Approved :: MIT License
Requires-Python: >=3.5
License-File: LICENSE
Requires-Dist: numpy
Requires-Dist: tqdm
